flytekitplugins_modin-1.16.12-py3.14-nspkg.pth
flytekitplugins/modin/__init__.py
flytekitplugins/modin/schema.py
flytekitplugins_modin-1.16.12.dist-info/METADATA
flytekitplugins_modin-1.16.12.dist-info/WHEEL
flytekitplugins_modin-1.16.12.dist-info/namespace_packages.txt
flytekitplugins_modin-1.16.12.dist-info/top_level.txt
flytekitplugins_modin-1.16.12.dist-info/RECORD
